<?xml version="1.0" encoding="utf-8"?>
<LanguageData>
  <!--The following translations were generated by https://www.deepl.com/-->
  <!-- EN: food type -->
  <DFoodTypeStat.label>тип еды</DFoodTypeStat.label>
  <!-- EN: The type and temperature preference of this food. -->
  <DFoodTypeStat.description>Тип и температурные предпочтения этой еды.</DFoodTypeStat.description>
  <DFoodTypeStat.labelForFullStatList>тип еды</DFoodTypeStat.labelForFullStatList>
  <!-- EN: current temperature -->
  <DTempStat.label>текущая температура</DTempStat.label>
  <!-- EN: The current temperature of this thing. -->
  <DTempStat.description>Текущая температура этой вещи.</DTempStat.description>
  <DTempStat.labelForFullStatList>текущая температура</DTempStat.labelForFullStatList>
</LanguageData>
